{
  "pools": [
    {
      "bonus_rolls": 0.0,
      "entries": [
        {
          "type": "minecraft:item",
          "functions": [
            {
              "add": false,
              "count": 1.0,
              "function": "minecraft:set_count"
            }
          ],
          "name": "minecraft:clay"
        },
        {
          "type": "minecraft:item",
          "functions": [
            {
              "add": false,
              "count": 4.0,
              "function": "minecraft:set_count"
            }
          ],
          "name": "minecraft:clay_ball"
        }
      ],
      "rolls": 1.0
    }
  ],
  "random_sequence": "todecoins:trade_tables/misc/clay_table"
}