{
    "type": "minecraft:entity",
    "pools": [
        {
            "bonus_rolls": 0.0,
            "entries": [
                {
                    "type": "minecraft:item",
                    "conditions": [
                        {
                            "condition": "todecoins:entity_type_tag_condition",
                            "tag": "forge:bee"
                        },
                        {
                            "condition": "todecoins:spring_condition"
                        }
                    ],
                    "name": "todecoins:collectible_coin_bee_copper"
                },
                {
                    "type": "minecraft:item",
                    "conditions": [
                        {
                            "condition": "todecoins:entity_type_tag_condition",
                            "tag": "forge:bee"
                        },
                        {
                            "condition": "todecoins:summer_condition"
                        }
                    ],
                    "name": "todecoins:collectible_coin_bee_iron"
                },
                {
                    "type": "minecraft:item",
                    "conditions": [
                        {
                            "condition": "todecoins:entity_type_tag_condition",
                            "tag": "forge:bee"
                        },
                        {
                            "condition": "todecoins:spring_condition"
                        }
                    ],
                    "name": "todecoins:collectible_coin_bee_gold"
                },
                {
                    "type": "minecraft:item",
                    "conditions": [
                        {
                            "condition": "todecoins:entity_type_tag_condition",
                            "tag": "forge:bee"
                        },
                        {
                            "condition": "todecoins:spring_condition"
                        }
                    ],
                    "name": "todecoins:collectible_coin_bee_netherite"
                }
            ],
            "rolls": 1.0
        }
    ]
}