{
  "pools": [
    {
      "bonus_rolls": 0.0,
      "entries": [
        {
          "type": "minecraft:item",
          "conditions": [
            {
              "condition": "todecoins:modloaded_condition",
              "modid": "create"
            }
          ],
          "name": "create:stressometer"
        },
        {
          "type": "minecraft:item",
          "conditions": [
            {
              "condition": "todecoins:modloaded_condition",
              "modid": "create"
            }
          ],
          "name": "create:speedometer"
        },
        {
          "type": "minecraft:item",
          "conditions": [
            {
              "condition": "todecoins:modloaded_condition",
              "modid": "create"
            }
          ],
          "name": "create:clipboard"
        },
        {
          "type": "minecraft:item",
          "conditions": [
            {
              "condition": "todecoins:modloaded_condition",
              "modid": "create"
            }
          ],
          "name": "create:super_glue"
        },
        {
          "type": "minecraft:item",
          "conditions": [
            {
              "condition": "todecoins:modloaded_condition",
              "modid": "create"
            }
          ],
          "name": "create:extendo_grip"
        },
        {
          "type": "minecraft:item",
          "conditions": [
            {
              "condition": "todecoins:modloaded_condition",
              "modid": "create"
            }
          ],
          "name": "create:wand_of_symmetry"
        },
        {
          "type": "minecraft:item",
          "conditions": [
            {
              "condition": "todecoins:modloaded_condition",
              "modid": "create"
            }
          ],
          "name": "create:empty_schematic"
        },
        {
          "type": "minecraft:tag",
          "conditions": [
            {
              "condition": "todecoins:modloaded_condition",
              "modid": "create"
            }
          ],
          "expand": true,
          "name": "create:toolboxes"
        },
        {
          "type": "minecraft:loot_table",
          "conditions": [
            {
              "condition": "minecraft:inverted",
              "term": {
                "condition": "todecoins:modloaded_condition",
                "modid": "create"
              }
            }
          ],
          "name": "todecoins:trade_tables/tools/iron_tier_tools"
        }
      ],
      "rolls": 1.0
    }
  ],
  "random_sequence": "todecoins:trade_tables/tools/engineer_tools"
}