{
  "type": "forge:conditional",
  "recipes": [
    {
      "conditions": [
        {
          "type": "forge:mod_loaded",
          "modid": "goblintraders"
        }
      ],
      "recipe": {
        "type": "todecoins:spawn_egg_shapeless",
        "group": "spawn_eggs",
        "ingredients": [
          {
            "tag": "forge:eggs"
          },
          {
            "tag": "forge:soul_binder"
          },
          {
            "tag": "forge:nuggets/netherite"
          },
          {
            "item": "minecraft:heart_of_the_sea"
          },
          {
            "item": "minecraft:emerald"
          },
          {
            "item": "minecraft:carrot"
          }
        ],
        "recipe_book_category": "MISC",
        "result": {
          "item": "goblintraders:vein_goblin_trader_spawn_egg"
        }
      }
    }
  ]
}