{
  "type": "todecoins:maps",
  "pools": [
    {
      "bonus_rolls": 0.0,
      "entries": [
        {
          "type": "minecraft:item",
          "functions": [
            {
              "decoration": "target_x",
              "destination": "todecoins:on_nether_fortress_explorer_maps",
              "function": "minecraft:exploration_map",
              "skip_existing_chunks": false,
              "zoom": 1
            },
            {
              "function": "minecraft:set_name",
              "name": {
                "translate": "filled_map.fortress"
              }
            }
          ],
          "name": "minecraft:map"
        },
        {
          "type": "minecraft:item",
          "functions": [
            {
              "decoration": "target_x",
              "destination": "todecoins:on_nether_fossil_explorer_maps",
              "function": "minecraft:exploration_map",
              "skip_existing_chunks": false,
              "zoom": 1
            },
            {
              "function": "minecraft:set_name",
              "name": {
                "translate": "filled_map.nether_fossil"
              }
            }
          ],
          "name": "minecraft:map"
        },
        {
          "type": "minecraft:item",
          "functions": [
            {
              "decoration": "target_x",
              "destination": "todecoins:on_bastion_remnant_explorer_maps",
              "function": "minecraft:exploration_map",
              "skip_existing_chunks": false,
              "zoom": 1
            },
            {
              "function": "minecraft:set_name",
              "name": {
                "translate": "filled_map.bastion_remnant"
              }
            }
          ],
          "name": "minecraft:map"
        },
        {
          "type": "minecraft:item",
          "functions": [
            {
              "decoration": "target_x",
              "destination": "todecoins:on_nether_ruined_portal_explorer_maps",
              "function": "minecraft:exploration_map",
              "skip_existing_chunks": false,
              "zoom": 1
            },
            {
              "function": "minecraft:set_name",
              "name": {
                "translate": "filled_map.ruined_portal_nether"
              }
            }
          ],
          "name": "minecraft:map"
        }
      ],
      "rolls": 1.0
    }
  ]
}