{
  "offers": {
    "apprentice": [
      {
        "type": "todecoins:loot_table_for_loot_table",
        "max_trades": 3,
        "offered_table": "todecoins:trade_tables/wandering/sell_two_emerald_value",
        "price_multiplier": 0.2,
        "requested_table": "todecoins:trade_tables/currency/two_emerald_value_currency",
        "trade_experience": 10
      },
      {
        "type": "todecoins:loot_table_for_loot_table",
        "max_trades": 3,
        "offered_table": "todecoins:trade_tables/wandering/sell_three_emerald_value",
        "price_multiplier": 0.2,
        "requested_table": "todecoins:trade_tables/currency/three_emerald_value_currency",
        "trade_experience": 10
      }
    ],
    "expert": [
      {
        "type": "todecoins:loot_table_for_loot_table",
        "max_trades": 3,
        "offered_table": "todecoins:trade_tables/wandering/sell_special",
        "price_multiplier": 0.2,
        "requested_table": "todecoins:trade_tables/currency/single_emerald_value_currency",
        "trade_experience": 20
      },
      {
        "type": "todecoins:loot_table_for_enchanted_item_table",
        "offered_table": "todecoins:trade_tables/tools/iron_tier_tools",
        "requested_table": "todecoins:trade_tables/currency/fourteen_emerald_value_currency",
        "trade_experience": 20
      }
    ],
    "journeyman": [
      {
        "type": "todecoins:loot_table_for_item",
        "max_trades": 3,
        "offered_item": "minecraft:slime_ball",
        "price_multiplier": 0.2,
        "requested_table": "todecoins:trade_tables/currency/four_emerald_value_currency",
        "trade_experience": 15
      },
      {
        "type": "todecoins:loot_table_for_loot_table",
        "max_trades": 3,
        "offered_table": "todecoins:trade_tables/wandering/sell_five_emerald_value",
        "price_multiplier": 0.2,
        "requested_table": "todecoins:trade_tables/currency/five_emerald_value_currency",
        "trade_experience": 15
      }
    ],
    "master": [
      {
        "type": "todecoins:loot_table_for_item",
        "max_trades": 3,
        "offered_item": "minecraft:blue_ice",
        "price_multiplier": 0.2,
        "requested_table": "todecoins:trade_tables/currency/single_emerald_value_currency",
        "trade_experience": 25
      },
      {
        "type": "todecoins:loot_table_for_loot_box",
        "display_name": "Mystery Loot Box",
        "loot_table": "minecraft:chests/abandoned_mineshaft",
        "max_trades": 1,
        "offered_item": "minecraft:shulker_box",
        "price_multiplier": 0.2,
        "requested_table": "todecoins:trade_tables/currency/sixteen_emerald_table",
        "trade_experience": 25
      }
    ],
    "novice": [
      {
        "type": "todecoins:loot_table_for_loot_table",
        "max_trades": 3,
        "offered_table": "todecoins:trade_tables/currency/single_emerald_value_currency",
        "price_multiplier": 0.2,
        "requested_table": "todecoins:trade_tables/wandering/purchase"
      },
      {
        "type": "todecoins:loot_table_for_tag_table",
        "max_trades": 3,
        "offered_item_count": 3,
        "offered_table": "todecoins:trade_tables/textiles/tagged_dyes_table",
        "price_multiplier": 0.2,
        "requested_table": "todecoins:trade_tables/currency/single_emerald_value_currency"
      }
    ]
  },
  "profession": "todevillagers:retired_trader"
}