{
  "parent": "todecoins:collectible/guardian_coins",
  "criteria": {
    "find_item.todecoins.collectible_coin_hero_copper": {
      "conditions": {
        "items": [
          {
            "items": [
              "todecoins:collectible_coin_hero_copper"
            ]
          }
        ]
      },
      "trigger": "minecraft:inventory_changed"
    },
    "find_item.todecoins.collectible_coin_hero_gold": {
      "conditions": {
        "items": [
          {
            "items": [
              "todecoins:collectible_coin_hero_gold"
            ]
          }
        ]
      },
      "trigger": "minecraft:inventory_changed"
    },
    "find_item.todecoins.collectible_coin_hero_iron": {
      "conditions": {
        "items": [
          {
            "items": [
              "todecoins:collectible_coin_hero_iron"
            ]
          }
        ]
      },
      "trigger": "minecraft:inventory_changed"
    },
    "find_item.todecoins.collectible_coin_hero_netherite": {
      "conditions": {
        "items": [
          {
            "items": [
              "todecoins:collectible_coin_hero_netherite"
            ]
          }
        ]
      },
      "trigger": "minecraft:inventory_changed"
    }
  },
  "display": {
    "announce_to_chat": true,
    "description": {
      "translate": "advancement.heroCoinSet.desc"
    },
    "frame": "task",
    "hidden": false,
    "icon": {
      "item": "todecoins:collectible_coin_hero_copper",
      "nbt": "{Damage:0}"
    },
    "show_toast": true,
    "title": {
      "translate": "advancement.heroCoinSet"
    }
  },
  "requirements": [
    [
      "find_item.todecoins.collectible_coin_hero_copper"
    ],
    [
      "find_item.todecoins.collectible_coin_hero_iron"
    ],
    [
      "find_item.todecoins.collectible_coin_hero_gold"
    ],
    [
      "find_item.todecoins.collectible_coin_hero_netherite"
    ]
  ]
}