{
  "parent": "todecoins:main/root",
  "criteria": {
    "find_four_leaf_clover": {
      "conditions": {
        "items": [
          {
            "items": [
              "todecoins:four_leaf_clover"
            ]
          }
        ]
      },
      "trigger": "minecraft:inventory_changed"
    }
  },
  "display": {
    "announce_to_chat": true,
    "description": {
      "translate": "advancement.luckyClover.desc"
    },
    "frame": "task",
    "hidden": true,
    "icon": {
      "item": "todecoins:four_leaf_clover"
    },
    "show_toast": true,
    "title": {
      "translate": "advancement.luckyClover"
    }
  },
  "requirements": [
    [
      "find_four_leaf_clover"
    ]
  ]
}