{
  "type": "minecraft:entity",
  "pools": [
    {
      "bonus_rolls": 1.0,
      "conditions": [
        {
          "condition": "minecraft:killed_by_player"
        }
      ],
      "entries": [
        {
          "type": "minecraft:loot_table",
          "conditions": [
            {
              "chance": 0.001,
              "condition": "minecraft:random_chance"
            },
            {
              "condition": "todecoins:entity_type_tag_condition",
              "tag": "forge:bosses"
            }
          ],
          "name": "todecoins:entity/coins/todecoins_lucky_coin_drops",
          "quality": 6
        },
        {
          "type": "minecraft:loot_table",
          "conditions": [
            {
              "condition": "todecoins:entity_type_tag_condition",
              "tag": "forge:bosses"
            }
          ],
          "name": "todecoins:entity/coins/todecoins_boss_copper_coin_drops"
        },
        {
          "type": "minecraft:loot_table",
          "conditions": [
            {
              "condition": "todecoins:entity_type_tag_condition",
              "tag": "forge:bosses"
            }
          ],
          "name": "todecoins:entity/coins/todecoins_boss_copper_iron_drops",
          "weight": 2
        },
        {
          "type": "minecraft:loot_table",
          "conditions": [
            {
              "condition": "todecoins:entity_type_tag_condition",
              "tag": "forge:bosses"
            }
          ],
          "name": "todecoins:entity/coins/todecoins_boss_gold_coin_drops",
          "quality": 1,
          "weight": 3
        },
        {
          "type": "minecraft:loot_table",
          "conditions": [
            {
              "condition": "todecoins:entity_type_tag_condition",
              "tag": "forge:bosses"
            },
            {
              "condition": "minecraft:location_check",
              "predicate": {
                "dimension": "minecraft:the_nether"
              }
            }
          ],
          "name": "todecoins:entity/coins/todecoins_boss_nether_gold_coin_drops",
          "quality": 1,
          "weight": 4
        },
        {
          "type": "minecraft:loot_table",
          "conditions": [
            {
              "condition": "todecoins:entity_type_tag_condition",
              "tag": "forge:bosses"
            },
            {
              "condition": "minecraft:location_check",
              "predicate": {
                "dimension": "minecraft:the_end"
              }
            }
          ],
          "name": "todecoins:entity/coins/todecoins_boss_endonian_coin_drops",
          "quality": 3,
          "weight": 5
        },
        {
          "type": "minecraft:loot_table",
          "conditions": [
            {
              "condition": "todecoins:entity_type_tag_condition",
              "tag": "forge:bosses"
            }
          ],
          "name": "todecoins:entity/notes/todecoins_boss_emerald_quarter_bank_note_drops",
          "quality": 2,
          "weight": 6
        },
        {
          "type": "minecraft:loot_table",
          "conditions": [
            {
              "condition": "todecoins:entity_type_tag_condition",
              "tag": "forge:bosses"
            }
          ],
          "name": "todecoins:entity/coins/todecoins_boss_netherite_coin_drops",
          "quality": 3,
          "weight": 7
        },
        {
          "type": "minecraft:loot_table",
          "conditions": [
            {
              "condition": "todecoins:entity_type_tag_condition",
              "tag": "forge:bosses"
            }
          ],
          "name": "todecoins:entity/notes/todecoins_boss_emerald_half_bank_note_drops",
          "quality": 3,
          "weight": 8
        },
        {
          "type": "minecraft:loot_table",
          "conditions": [
            {
              "condition": "todecoins:entity_type_tag_condition",
              "tag": "forge:bosses"
            }
          ],
          "name": "todecoins:entity/notes/todecoins_boss_emerald_bank_note_drops",
          "quality": 4,
          "weight": 9
        },
        {
          "type": "minecraft:loot_table",
          "conditions": [
            {
              "condition": "todecoins:entity_type_tag_condition",
              "tag": "forge:bosses"
            }
          ],
          "name": "todecoins:entity/coins/todecoins_boss_netherite_coin_drops",
          "quality": 5,
          "weight": 10
        },
        {
          "type": "minecraft:empty"
        }
      ],
      "functions": [
        {
          "count": 1.0,
          "function": "minecraft:looting_enchant"
        }
      ],
      "rolls": {
        "type": "minecraft:uniform",
        "max": 15.0,
        "min": 10.0
      }
    }
  ]
}